setup.py
qh_probability/Binomialdistribution.py
qh_probability/Gaussiandistribution.py
qh_probability/Generaldistribution.py
qh_probability/__init__.py
qh_probability.egg-info/PKG-INFO
qh_probability.egg-info/SOURCES.txt
qh_probability.egg-info/dependency_links.txt
qh_probability.egg-info/not-zip-safe
qh_probability.egg-info/top_level.txt