Metadata-Version: 1.0
Name: qh-probability
Version: 1.0
Summary: Gaussian and Binomial distributions
Home-page: UNKNOWN
Author: Qin Hu
Author-email: erinqhu08@gmail.com
License: UNKNOWN
Platform: UNKNOWN
